MANIFEST.in
README.md
setup.cfg
setup.py
dex/__init__.py
dex/admin.py
dex/apps.py
dex/conf.py
dex/models.py
dex/msgs.py
dex/tests.py
dex/urls.py
dex/utils.py
dex/views.py
dex/db/__init__.py
dex/db/__pycache__/__init__.cpython-35.pyc
dex/db/__pycache__/__init__.cpython-36.pyc
dex/db/django/__init__.py
dex/db/django/__pycache__/__init__.cpython-35.pyc
dex/db/django/__pycache__/__init__.cpython-36.pyc
dex/db/influxdb/__init__.py
dex/db/influxdb/serializers.py
dex/db/influxdb/__pycache__/__init__.cpython-35.pyc
dex/db/influxdb/__pycache__/serializers.cpython-35.pyc
dex/export/__init__.py
dex/export/tofiles.py
dex/export/__pycache__/__init__.cpython-35.pyc
dex/export/__pycache__/__init__.cpython-36.pyc
dex/management/__init__.py
dex/management/__init__.pyc
dex/management/__pycache__/__init__.cpython-35.pyc
dex/management/__pycache__/__init__.cpython-36.pyc
dex/management/commands/__init__.py
dex/management/commands/__init__.pyc
dex/management/commands/clonedb.py
dex/management/commands/__pycache__/__init__.cpython-35.pyc
dex/management/commands/__pycache__/__init__.cpython-36.pyc
dex/management/commands/__pycache__/build_navlinks.cpython-35.pyc
dex/management/commands/__pycache__/build_routes.cpython-35.pyc
dex/management/commands/__pycache__/clonedb.cpython-35.pyc
dex/management/commands/__pycache__/clonedb.cpython-36.pyc
dex/management/commands/__pycache__/dexport.cpython-35.pyc
dex/management/commands/__pycache__/inflexport.cpython-35.pyc
dex/management/commands/__pycache__/testcom.cpython-35.pyc
dex/migrations/__init__.py
dex/migrations/__pycache__/__init__.cpython-35.pyc
dex/migrations/__pycache__/__init__.cpython-36.pyc
dex/terminal/commands.py
dex/terminal/__pycache__/commands.cpython-35.pyc
dex/terminal/__pycache__/commands.cpython-36.pyc
django_dex.egg-info/PKG-INFO
django_dex.egg-info/SOURCES.txt
django_dex.egg-info/dependency_links.txt
django_dex.egg-info/not-zip-safe
django_dex.egg-info/requires.txt
django_dex.egg-info/top_level.txt