Metadata-Version: 1.1
Name: django-dex
Version: 0.3.3
Summary: Database export tools for Django
Home-page: https://github.com/synw/django-dex
Author: synw
Author-email: synwe@yahoo.com
License: UNKNOWN
Download-URL: https://github.com/synw/django-dex/releases/tag/0.3.3
Keywords: django,database_export
Platform: UNKNOWN
Classifier: Development Status :: 3 - Alpha
Classifier: Framework :: Django :: 1.11
Classifier: Intended Audience :: Developers
Classifier: License :: OSI Approved :: MIT License
Classifier: Programming Language :: Python :: 3.6
